{
  "version": 2.0,
  "questions": [
    {
      "question": "The process of selecting the desired frequency from a composite wave is called.",
      "answers": {
        "a": "Filtering",
        "b": "Demodulation",
        "c": "Rectification",
        "d": "Tuning"
      },
      "explanations": {
        "a": "Filtering removes unwanted components from a signal.",
        "b": "Demodulation extracts the original information signal.",
        "c": "Rectification converts AC to DC.",
        "d": "Tuning is the correct answer; it selects the desired frequency."
      },
      "correctAnswer": "d",
      "difficulty": "beginner"
    },
    {
      "question": "Tuning circuit use the principle of......",
      "answers": {
        "a": "Modulation",
        "b": "Maximum energy transfer",
        "c": "Mutual inductance",
        "d": "Resonance"
      },
      "explanations": {
        "a": "Modulation refers to altering the signal.",
        "b": "Maximum energy transfer is a general principle.",
        "c": "Mutual inductance relates to coupled coils.",
        "d": "Resonance is the correct principle used in tuning circuits."
      },
      "correctAnswer": "d",
      "difficulty": "beginner"
    }
}
